convert_to_time/__init__.py
convert_to_time/convertToTime.py
convert_to_time-0.0.1.dist-info/DESCRIPTION.rst
convert_to_time-0.0.1.dist-info/METADATA
convert_to_time-0.0.1.dist-info/RECORD
convert_to_time-0.0.1.dist-info/WHEEL
convert_to_time-0.0.1.dist-info/metadata.json
convert_to_time-0.0.1.dist-info/top_level.txt
